{
  "successful": [
    {
      "id": 2,
      "foldingUserName": "User2",
      "displayName": "User2",
      "passkey": "fc7d6837************************",
      "category": "AMD_GPU",
      "hardware": {
        "id": 2,
        "hardwareName": "Hardware2",
        "displayName": "Hardware2",
        "hardwareMake": "NVIDIA",
        "hardwareType": "GPU",
        "multiplier": 21.33,
        "averagePpd": 1
      },
      "team": {
        "id": 1,
        "teamName": "Team1"
      },
      "userIsCaptain": false
    }
  ],
  "unsuccessful": [
    {
      "invalidObject": {
        "foldingUserName": "User1",
        "displayName": "User1",
        "passkey": "fc7d6837269d86784d8bfd0b386d6bca",
        "category": "WILDCARD",
        "profileLink": "https://forums.extremehw.net/",
        "liveStatsLink": "http://teamcomp.axihub.ca/",
        "hardwareId": 1,
        "teamId": 1,
        "userIsCaptain": true
      },
      "errors": [
        "User 'User1' has 0 Work Units with passkey 'fc7d6837269d86784d8bfd0b386d6bca', there must be at least one completed Work Unit before adding the user"
      ]
    }
  ]
}